xapi_service/__init__.py
xapi_service/connect.py
xapi_service/servers.py
xapi_service-0.0.3.dist-info/LICENSE
xapi_service-0.0.3.dist-info/METADATA
xapi_service-0.0.3.dist-info/WHEEL
xapi_service-0.0.3.dist-info/top_level.txt
xapi_service-0.0.3.dist-info/RECORD
